razorbill/__init__.py
razorbill/_types.py
razorbill/builder.py
razorbill/connectors/__init__.py
razorbill/connectors/alchemy/__init__.py
razorbill/connectors/alchemy/_types.py
razorbill/connectors/alchemy/connector.py
razorbill/connectors/alchemy/converter.py
razorbill/connectors/alchemy/exceptions.py
razorbill/connectors/alchemy/select.py
razorbill/connectors/alchemy/utils.py
razorbill/connectors/base.py
razorbill/connectors/memory.py
razorbill/connectors/mongo/__init__.py
razorbill/connectors/mongo/mongo.py
razorbill/connectors/mongo/utils.py
razorbill/crud.py
razorbill/deps.py
razorbill/exceptions.py
razorbill/router.py
razorbill/schema.py
razorbill/utils.py
razorbill-0.2.9.dist-info/LICENSE
razorbill-0.2.9.dist-info/WHEEL
razorbill-0.2.9.dist-info/METADATA
razorbill-0.2.9.dist-info/RECORD
