Metadata-Version: 2.1
Name: razorbill
Version: 0.2.9
Summary: Razorbill is a framework for quickly creating API applications using only the description of the data model.
Author: Nikita Irgashev
Author-email: nik.irg@yandex.ru
Requires-Python: >=3.11,<4.0
Classifier: Programming Language :: Python :: 3
Classifier: Programming Language :: Python :: 3.11
Requires-Dist: aiosqlite (>=0.19.0,<0.20.0)
Requires-Dist: alembic (>=1.12.0,<2.0.0)
Requires-Dist: asyncpg (>=0.28.0,<0.29.0)
Requires-Dist: asyncpgsa (>=0.27.1,<0.28.0)
Requires-Dist: beanie (>=1.21.0,<2.0.0)
Requires-Dist: fastapi (>=0.110.1,<0.111.0)
Requires-Dist: greenlet (>=2.0.2,<3.0.0)
Requires-Dist: loguru (>=0.7.0,<0.8.0)
Requires-Dist: motor (>=3.3.1,<4.0.0)
Requires-Dist: psycopg2-binary (>=2.9.7,<3.0.0)
Requires-Dist: pytest (>=7.4.0,<8.0.0)
Requires-Dist: pytest-asyncio (>=0.21.1,<0.22.0)
Requires-Dist: sqlalchemy (>=2.0.17,<3.0.0)
Requires-Dist: uvicorn (>=0.23.2,<0.24.0)
